sword3client/__init__.py
sword3client/client.py
sword3client/connection/__init__.py
sword3client/connection/connection.py
sword3client/connection/connection_requests.py
sword3client/lib/__init__.py
sword3client/lib/paths.py
sword3client/models/__init__.py
sword3client/models/sword_response.py
sword3client/test/__init__.py
sword3client/test/functional/__init__.py
sword3client/test/functional/test_invenio.py
sword3client/test/mocks/__init__.py
sword3client/test/mocks/connection.py
sword3client/test/mocks/metadata.py
sword3client/test/unit/__init__.py
sword3client/test/unit/test_binary_deposit.py
sword3client/test/unit/test_by_reference_deposit.py
sword3client/test/unit/test_file.py
sword3client/test/unit/test_metadata_and_by_reference.py
sword3client/test/unit/test_metadata_deposit.py
sword3client/test/unit/test_object_methods.py
sword3client/test/unit/test_segmented.py
sword3client/test/unit/test_service.py
sword3client-0.1.dist-info/METADATA
sword3client-0.1.dist-info/WHEEL
sword3client-0.1.dist-info/top_level.txt
sword3client-0.1.dist-info/RECORD
