Metadata-Version: 2.1
Name: sword3client
Version: 0.1
Summary: SWORDv3 Client Library
Home-page: http://cottagelabs.com/
Author: Cottage Labs
Author-email: richard@cottagelabs.com
License: Apache2
Platform: UNKNOWN
Requires-Dist: sword3common
Provides-Extra: docs
Requires-Dist: Sphinx ; extra == 'docs'
Requires-Dist: sphinx-autodoc-annotation ; extra == 'docs'
Provides-Extra: test
Requires-Dist: nose ; extra == 'test'
